{
    "swagger": "2.0",
    "info": {
        "description": "Micorservice for handling admin products.",
        "title": "Swagger Products Admin Microservice",
        "termsOfService": "http://swagger.io/terms/",
        "contact": {
            "name": "API Support",
            "url": "http://www.swagger.io/support",
            "email": "support@swagger.io"
        },
        "license": {
            "name": "Apache 2.0",
            "url": "http://www.apache.org/licenses/LICENSE-2.0.html"
        },
        "version": "1.0"
    },
    "host": "http:38.84.28.237:30201",
    "basePath": "/api/rest_admin/products/",
    "paths": {
        "/": {
            "get": {
                "description": "products get API",
                "consumes": [
                    "application/json"
                ],
                "produces": [
                    "application/json"
                ],
                "tags": [
                    "Products"
                ],
                "summary": "Get All Products",
                "responses": {
                    "200": {
                        "description": "OK",
                        "schema": {
                            "$ref": "#/definitions/responses.ProductsMessage"
                        }
                    },
                    "400": {
                        "description": "Bad Request",
                        "schema": {
                            "$ref": "#/definitions/responses.MessageResponse"
                        }
                    },
                    "500": {
                        "description": "Internal Server Error",
                        "schema": {
                            "$ref": "#/definitions/responses.MessageResponse"
                        }
                    },
                    "502": {
                        "description": "Bad Gateway",
                        "schema": {
                            "$ref": "#/definitions/responses.MessageResponse"
                        }
                    }
                }
            },
            "post": {
                "description": "product post API",
                "consumes": [
                    "application/json"
                ],
                "produces": [
                    "application/json"
                ],
                "tags": [
                    "Products"
                ],
                "summary": "Add Products",
                "parameters": [
                    {
                        "description": "product request structure",
                        "name": "product",
                        "in": "body",
                        "required": true,
                        "schema": {
                            "$ref": "#/definitions/requests.ProductRequest"
                        }
                    }
                ],
                "responses": {
                    "200": {
                        "description": "OK",
                        "schema": {
                            "$ref": "#/definitions/responses.MessageResponse"
                        }
                    },
                    "400": {
                        "description": "Bad Request",
                        "schema": {
                            "$ref": "#/definitions/responses.MessageResponse"
                        }
                    },
                    "500": {
                        "description": "Internal Server Error",
                        "schema": {
                            "$ref": "#/definitions/responses.MessageResponse"
                        }
                    },
                    "502": {
                        "description": "Bad Gateway",
                        "schema": {
                            "$ref": "#/definitions/responses.MessageResponse"
                        }
                    }
                }
            }
        },
        "/search/category/{id}": {
            "get": {
                "description": "product search API",
                "consumes": [
                    "application/json"
                ],
                "produces": [
                    "application/json"
                ],
                "tags": [
                    "Search"
                ],
                "summary": "Search Products by CategoryID",
                "parameters": [
                    {
                        "type": "string",
                        "description": "categoryID",
                        "name": "id",
                        "in": "path",
                        "required": true
                    }
                ],
                "responses": {
                    "200": {
                        "description": "OK",
                        "schema": {
                            "$ref": "#/definitions/responses.ProductsMessage"
                        }
                    },
                    "400": {
                        "description": "Bad Request",
                        "schema": {
                            "$ref": "#/definitions/responses.MessageResponse"
                        }
                    },
                    "500": {
                        "description": "Internal Server Error",
                        "schema": {
                            "$ref": "#/definitions/responses.MessageResponse"
                        }
                    },
                    "502": {
                        "description": "Bad Gateway",
                        "schema": {
                            "$ref": "#/definitions/responses.MessageResponse"
                        }
                    }
                }
            }
        },
        "/search/keyword/{keyword}": {
            "get": {
                "description": "product search API",
                "consumes": [
                    "application/json"
                ],
                "produces": [
                    "application/json"
                ],
                "tags": [
                    "Search"
                ],
                "summary": "Search Products by Keyword",
                "parameters": [
                    {
                        "type": "string",
                        "description": "search keyword",
                        "name": "keyword",
                        "in": "path",
                        "required": true
                    }
                ],
                "responses": {
                    "200": {
                        "description": "OK",
                        "schema": {
                            "$ref": "#/definitions/responses.ProductsMessage"
                        }
                    },
                    "400": {
                        "description": "Bad Request",
                        "schema": {
                            "$ref": "#/definitions/responses.MessageResponse"
                        }
                    },
                    "500": {
                        "description": "Internal Server Error",
                        "schema": {
                            "$ref": "#/definitions/responses.MessageResponse"
                        }
                    },
                    "502": {
                        "description": "Bad Gateway",
                        "schema": {
                            "$ref": "#/definitions/responses.MessageResponse"
                        }
                    }
                }
            }
        },
        "/search/manufacturer/{id}": {
            "get": {
                "description": "product search API",
                "consumes": [
                    "application/json"
                ],
                "produces": [
                    "application/json"
                ],
                "tags": [
                    "Search"
                ],
                "summary": "Search Products by ManufacturerID",
                "parameters": [
                    {
                        "type": "string",
                        "description": "manufacturerID",
                        "name": "id",
                        "in": "path",
                        "required": true
                    }
                ],
                "responses": {
                    "200": {
                        "description": "OK",
                        "schema": {
                            "$ref": "#/definitions/responses.ProductsMessage"
                        }
                    },
                    "400": {
                        "description": "Bad Request",
                        "schema": {
                            "$ref": "#/definitions/responses.MessageResponse"
                        }
                    },
                    "500": {
                        "description": "Internal Server Error",
                        "schema": {
                            "$ref": "#/definitions/responses.MessageResponse"
                        }
                    },
                    "502": {
                        "description": "Bad Gateway",
                        "schema": {
                            "$ref": "#/definitions/responses.MessageResponse"
                        }
                    }
                }
            }
        },
        "/search/start/{price}": {
            "get": {
                "description": "product search API",
                "consumes": [
                    "application/json"
                ],
                "produces": [
                    "application/json"
                ],
                "tags": [
                    "Search"
                ],
                "summary": "Search Products by Starting Price",
                "parameters": [
                    {
                        "type": "string",
                        "description": "Starting Price",
                        "name": "price",
                        "in": "path",
                        "required": true
                    }
                ],
                "responses": {
                    "200": {
                        "description": "OK",
                        "schema": {
                            "$ref": "#/definitions/responses.ProductsMessage"
                        }
                    },
                    "400": {
                        "description": "Bad Request",
                        "schema": {
                            "$ref": "#/definitions/responses.MessageResponse"
                        }
                    },
                    "500": {
                        "description": "Internal Server Error",
                        "schema": {
                            "$ref": "#/definitions/responses.MessageResponse"
                        }
                    },
                    "502": {
                        "description": "Bad Gateway",
                        "schema": {
                            "$ref": "#/definitions/responses.MessageResponse"
                        }
                    }
                }
            }
        },
        "/{id}": {
            "put": {
                "description": "product put API",
                "consumes": [
                    "application/json"
                ],
                "produces": [
                    "application/json"
                ],
                "tags": [
                    "Products"
                ],
                "summary": "Update Products",
                "parameters": [
                    {
                        "type": "string",
                        "description": "produtID",
                        "name": "id",
                        "in": "path",
                        "required": true
                    },
                    {
                        "description": "product request structure",
                        "name": "product",
                        "in": "body",
                        "required": true,
                        "schema": {
                            "$ref": "#/definitions/requests.ProductIDRequest"
                        }
                    }
                ],
                "responses": {
                    "200": {
                        "description": "OK",
                        "schema": {
                            "$ref": "#/definitions/responses.MessageResponse"
                        }
                    },
                    "400": {
                        "description": "Bad Request",
                        "schema": {
                            "$ref": "#/definitions/responses.MessageResponse"
                        }
                    },
                    "500": {
                        "description": "Internal Server Error",
                        "schema": {
                            "$ref": "#/definitions/responses.MessageResponse"
                        }
                    },
                    "502": {
                        "description": "Bad Gateway",
                        "schema": {
                            "$ref": "#/definitions/responses.MessageResponse"
                        }
                    }
                }
            },
            "delete": {
                "description": "product delete API",
                "consumes": [
                    "application/json"
                ],
                "produces": [
                    "application/json"
                ],
                "tags": [
                    "Products"
                ],
                "summary": "Delete Products",
                "parameters": [
                    {
                        "type": "string",
                        "description": "produtID",
                        "name": "id",
                        "in": "path",
                        "required": true
                    }
                ],
                "responses": {
                    "200": {
                        "description": "OK",
                        "schema": {
                            "$ref": "#/definitions/responses.MessageResponse"
                        }
                    },
                    "400": {
                        "description": "Bad Request",
                        "schema": {
                            "$ref": "#/definitions/responses.MessageResponse"
                        }
                    },
                    "500": {
                        "description": "Internal Server Error",
                        "schema": {
                            "$ref": "#/definitions/responses.MessageResponse"
                        }
                    },
                    "502": {
                        "description": "Bad Gateway",
                        "schema": {
                            "$ref": "#/definitions/responses.MessageResponse"
                        }
                    }
                }
            }
        }
    },
    "definitions": {
        "domain.Product": {
            "type": "object",
            "required": [
                "height",
                "image",
                "length",
                "manufacturer_id",
                "minimum",
                "model",
                "points",
                "price",
                "product_category",
                "product_description",
                "product_related",
                "product_seo_url",
                "quantity",
                "reward",
                "shipping_id",
                "sku",
                "weight",
                "width"
            ],
            "properties": {
                "_id": {
                    "type": "integer"
                },
                "height": {
                    "type": "integer"
                },
                "image": {
                    "type": "string"
                },
                "length": {
                    "type": "integer"
                },
                "manufacturer_id": {
                    "type": "integer"
                },
                "minimum": {
                    "type": "integer"
                },
                "model": {
                    "type": "string"
                },
                "points": {
                    "type": "integer"
                },
                "price": {
                    "type": "string"
                },
                "product_category": {
                    "type": "array",
                    "items": {
                        "type": "integer"
                    }
                },
                "product_description": {
                    "type": "array",
                    "items": {
                        "$ref": "#/definitions/domain.ProductDescription"
                    }
                },
                "product_related": {
                    "type": "array",
                    "items": {
                        "type": "integer"
                    }
                },
                "product_seo_url": {
                    "$ref": "#/definitions/domain.ProductSeoUrl"
                },
                "quantity": {
                    "type": "integer"
                },
                "reward": {
                    "type": "integer"
                },
                "shipping_id": {
                    "type": "integer"
                },
                "sku": {
                    "type": "string"
                },
                "weight": {
                    "type": "integer"
                },
                "width": {
                    "type": "integer"
                }
            }
        },
        "domain.ProductDescription": {
            "type": "object",
            "properties": {
                "description": {
                    "type": "string"
                },
                "language_id": {
                    "type": "integer"
                },
                "meta_description": {
                    "type": "string"
                },
                "meta_keyword": {
                    "type": "string"
                },
                "meta_title": {
                    "type": "string"
                },
                "name": {
                    "type": "string"
                },
                "tag": {
                    "type": "string"
                }
            }
        },
        "domain.ProductSeoUrl": {
            "type": "object",
            "properties": {
                "keyword": {
                    "type": "string"
                },
                "language_id": {
                    "type": "integer"
                },
                "store_id": {
                    "type": "integer"
                }
            }
        },
        "requests.ProductIDRequest": {
            "type": "object",
            "properties": {
                "product": {
                    "$ref": "#/definitions/domain.Product"
                }
            }
        },
        "requests.ProductRequest": {
            "type": "object",
            "required": [
                "height",
                "image",
                "length",
                "manufacturer_id",
                "minimum",
                "model",
                "points",
                "price",
                "product_category",
                "product_description",
                "product_related",
                "product_seo_url",
                "quantity",
                "reward",
                "shipping_id",
                "sku",
                "weight",
                "width"
            ],
            "properties": {
                "height": {
                    "type": "integer"
                },
                "image": {
                    "type": "string"
                },
                "length": {
                    "type": "integer"
                },
                "manufacturer_id": {
                    "type": "integer"
                },
                "minimum": {
                    "type": "integer"
                },
                "model": {
                    "type": "string"
                },
                "points": {
                    "type": "integer"
                },
                "price": {
                    "type": "string"
                },
                "product_category": {
                    "type": "array",
                    "items": {
                        "type": "integer"
                    }
                },
                "product_description": {
                    "type": "array",
                    "items": {
                        "$ref": "#/definitions/domain.ProductDescription"
                    }
                },
                "product_related": {
                    "type": "array",
                    "items": {
                        "type": "integer"
                    }
                },
                "product_seo_url": {
                    "$ref": "#/definitions/domain.ProductSeoUrl"
                },
                "quantity": {
                    "type": "integer"
                },
                "reward": {
                    "type": "integer"
                },
                "shipping_id": {
                    "type": "integer"
                },
                "sku": {
                    "type": "string"
                },
                "weight": {
                    "type": "integer"
                },
                "width": {
                    "type": "integer"
                }
            }
        },
        "responses.MessageResponse": {
            "type": "object",
            "properties": {
                "message": {
                    "type": "string"
                }
            }
        },
        "responses.ProductsMessage": {
            "type": "object",
            "properties": {
                "products": {
                    "type": "array",
                    "items": {
                        "$ref": "#/definitions/domain.Product"
                    }
                }
            }
        }
    }
}